omu/__init__.py
omu/address.py
omu/app.py
omu/brand.py
omu/bytebuffer.py
omu/errors.py
omu/event_emitter.py
omu/helper.py
omu/identifier.py
omu/model.py
omu/omu.py
omu/plugin.py
omu/result.py
omu/serializer.py
omu/token.py
omu/version.py
omu/api/__init__.py
omu/api/extension.py
omu/api/asset/__init__.py
omu/api/asset/extension.py
omu/api/dashboard/__init__.py
omu/api/dashboard/extension.py
omu/api/dashboard/packets.py
omu/api/endpoint/__init__.py
omu/api/endpoint/endpoint.py
omu/api/endpoint/extension.py
omu/api/endpoint/packets.py
omu/api/http/__init__.py
omu/api/http/extension.py
omu/api/i18n/__init__.py
omu/api/i18n/extension.py
omu/api/logger/__init__.py
omu/api/logger/extension.py
omu/api/logger/packets.py
omu/api/permission/__init__.py
omu/api/permission/extension.py
omu/api/permission/permission.py
omu/api/plugin/__init__.py
omu/api/plugin/extension.py
omu/api/plugin/package_info.py
omu/api/plugin/plugin.py
omu/api/registry/__init__.py
omu/api/registry/extension.py
omu/api/registry/packets.py
omu/api/registry/registry.py
omu/api/server/__init__.py
omu/api/server/extension.py
omu/api/server/types.py
omu/api/session/__init__.py
omu/api/session/extension.py
omu/api/signal/__init__.py
omu/api/signal/extension.py
omu/api/signal/packets.py
omu/api/signal/signal.py
omu/api/table/__init__.py
omu/api/table/extension.py
omu/api/table/packets.py
omu/api/table/table.py
omu/interface/__init__.py
omu/interface/keyable.py
omu/interface/named.py
omu/localization/__init__.py
omu/localization/locale.py
omu/localization/localization.py
omu/network/__init__.py
omu/network/connection.py
omu/network/encryption.py
omu/network/network.py
omu/network/packet_mapper.py
omu/network/websocket_connection.py
omu/network/packet/__init__.py
omu/network/packet/packet.py
omu/network/packet/packet_types.py
omu-0.9.50.dist-info/METADATA
omu-0.9.50.dist-info/WHEEL
omu-0.9.50.dist-info/RECORD
