Metadata-Version: 2.4
Name: omu
Version: 0.9.50
Summary: OMUAPPS Python Implementation
Author-email: am230 <111672334+am230@users.noreply.github.com>
Requires-Python: >=3.12
Requires-Dist: aiohttp>=3.10.6
Requires-Dist: loguru>=0.7.2
